<annotation>
	<folder>VOC2007</folder>
	<filename>source_aachen_000106_000019_leftImg8bit.jpg</filename>
	<source>
		<database>The VOC2007 Database</database>
		<annotation>PASCAL VOC2007</annotation>
		<image>flickr</image>
		<flickrid>0</flickrid>
	</source>
	<owner>
		<flickrid>rtz</flickrid>
		<name>?</name>
	</owner>
	<size>
		<width>2048</width>
		<height>1024</height>
		<deep>3</deep>
	</size>
	<segmented>0</segmented>
	<object>
		<name>person</name>
		<pose>Frontal</pose>
		<truncated>0</truncated>
		<difficult>0</difficult>
		<bndbox>
			<xmin>1479</xmin>
			<ymin>394</ymin>
			<xmax>1488</xmax>
			<ymax>427</ymax>
		</bndbox>
	</object>
	<object>
		<name>person</name>
		<pose>Frontal</pose>
		<truncated>0</truncated>
		<difficult>0</difficult>
		<bndbox>
			<xmin>1503</xmin>
			<ymin>393</ymin>
			<xmax>1512</xmax>
			<ymax>428</ymax>
		</bndbox>
	</object>
	<object>
		<name>person</name>
		<pose>Frontal</pose>
		<truncated>0</truncated>
		<difficult>0</difficult>
		<bndbox>
			<xmin>1529</xmin>
			<ymin>394</ymin>
			<xmax>1549</xmax>
			<ymax>433</ymax>
		</bndbox>
	</object>
	<object>
		<name>person</name>
		<pose>Frontal</pose>
		<truncated>0</truncated>
		<difficult>0</difficult>
		<bndbox>
			<xmin>2012</xmin>
			<ymin>369</ymin>
			<xmax>2048</xmax>
			<ymax>489</ymax>
		</bndbox>
	</object>
	<object>
		<name>person</name>
		<pose>Frontal</pose>
		<truncated>0</truncated>
		<difficult>0</difficult>
		<bndbox>
			<xmin>1654</xmin>
			<ymin>413</ymin>
			<xmax>1664</xmax>
			<ymax>424</ymax>
		</bndbox>
	</object>
	<object>
		<name>car</name>
		<pose>Frontal</pose>
		<truncated>0</truncated>
		<difficult>0</difficult>
		<bndbox>
			<xmin>1559</xmin>
			<ymin>428</ymin>
			<xmax>1635</xmax>
			<ymax>523</ymax>
		</bndbox>
	</object>
	<object>
		<name>car</name>
		<pose>Frontal</pose>
		<truncated>0</truncated>
		<difficult>0</difficult>
		<bndbox>
			<xmin>1599</xmin>
			<ymin>417</ymin>
			<xmax>1764</xmax>
			<ymax>534</ymax>
		</bndbox>
	</object>
	<object>
		<name>car</name>
		<pose>Frontal</pose>
		<truncated>0</truncated>
		<difficult>0</difficult>
		<bndbox>
			<xmin>207</xmin>
			<ymin>392</ymin>
			<xmax>579</xmax>
			<ymax>585</ymax>
		</bndbox>
	</object>
	<object>
		<name>bus</name>
		<pose>Frontal</pose>
		<truncated>0</truncated>
		<difficult>0</difficult>
		<bndbox>
			<xmin>511</xmin>
			<ymin>224</ymin>
			<xmax>1109</xmax>
			<ymax>575</ymax>
		</bndbox>
	</object>
	<object>
		<name>person</name>
		<pose>Frontal</pose>
		<truncated>0</truncated>
		<difficult>0</difficult>
		<bndbox>
			<xmin>1281</xmin>
			<ymin>408</ymin>
			<xmax>1309</xmax>
			<ymax>456</ymax>
		</bndbox>
	</object>
	<object>
		<name>car</name>
		<pose>Frontal</pose>
		<truncated>0</truncated>
		<difficult>0</difficult>
		<bndbox>
			<xmin>1229</xmin>
			<ymin>423</ymin>
			<xmax>1302</xmax>
			<ymax>511</ymax>
		</bndbox>
	</object>
	<object>
		<name>car</name>
		<pose>Frontal</pose>
		<truncated>0</truncated>
		<difficult>0</difficult>
		<bndbox>
			<xmin>1023</xmin>
			<ymin>376</ymin>
			<xmax>1288</xmax>
			<ymax>598</ymax>
		</bndbox>
	</object>
	<object>
		<name>car</name>
		<pose>Frontal</pose>
		<truncated>0</truncated>
		<difficult>0</difficult>
		<bndbox>
			<xmin>1384</xmin>
			<ymin>419</ymin>
			<xmax>1439</xmax>
			<ymax>461</ymax>
		</bndbox>
	</object>
	<object>
		<name>person</name>
		<pose>Frontal</pose>
		<truncated>0</truncated>
		<difficult>0</difficult>
		<bndbox>
			<xmin>1751</xmin>
			<ymin>410</ymin>
			<xmax>1778</xmax>
			<ymax>463</ymax>
		</bndbox>
	</object>
	<object>
		<name>bicycle</name>
		<pose>Frontal</pose>
		<truncated>0</truncated>
		<difficult>0</difficult>
		<bndbox>
			<xmin>1516</xmin>
			<ymin>451</ymin>
			<xmax>1573</xmax>
			<ymax>493</ymax>
		</bndbox>
	</object>
	<object>
		<name>person</name>
		<pose>Frontal</pose>
		<truncated>0</truncated>
		<difficult>0</difficult>
		<bndbox>
			<xmin>1441</xmin>
			<ymin>399</ymin>
			<xmax>1453</xmax>
			<ymax>439</ymax>
		</bndbox>
	</object>
	<object>
		<name>person</name>
		<pose>Frontal</pose>
		<truncated>0</truncated>
		<difficult>0</difficult>
		<bndbox>
			<xmin>1516</xmin>
			<ymin>401</ymin>
			<xmax>1532</xmax>
			<ymax>438</ymax>
		</bndbox>
	</object>
	<object>
		<name>person</name>
		<pose>Frontal</pose>
		<truncated>0</truncated>
		<difficult>0</difficult>
		<bndbox>
			<xmin>1554</xmin>
			<ymin>395</ymin>
			<xmax>1566</xmax>
			<ymax>433</ymax>
		</bndbox>
	</object>
	<object>
		<name>person</name>
		<pose>Frontal</pose>
		<truncated>0</truncated>
		<difficult>0</difficult>
		<bndbox>
			<xmin>1545</xmin>
			<ymin>418</ymin>
			<xmax>1562</xmax>
			<ymax>453</ymax>
		</bndbox>
	</object>
	<object>
		<name>car</name>
		<pose>Frontal</pose>
		<truncated>0</truncated>
		<difficult>0</difficult>
		<bndbox>
			<xmin>2009</xmin>
			<ymin>468</ymin>
			<xmax>2048</xmax>
			<ymax>680</ymax>
		</bndbox>
	</object>
	<object>
		<name>person</name>
		<pose>Frontal</pose>
		<truncated>0</truncated>
		<difficult>0</difficult>
		<bndbox>
			<xmin>1321</xmin>
			<ymin>412</ymin>
			<xmax>1327</xmax>
			<ymax>436</ymax>
		</bndbox>
	</object>
	<object>
		<name>person</name>
		<pose>Frontal</pose>
		<truncated>0</truncated>
		<difficult>0</difficult>
		<bndbox>
			<xmin>2018</xmin>
			<ymin>370</ymin>
			<xmax>2048</xmax>
			<ymax>489</ymax>
		</bndbox>
	</object>
</annotation>