<annotation>
	<folder>VOC2007</folder>
	<filename>target_lindau_000055_000019_leftImg8bit_foggy_beta_0.02.jpg</filename>
	<source>
		<database>The VOC2007 Database</database>
		<annotation>PASCAL VOC2007</annotation>
		<image>flickr</image>
		<flickrid>0</flickrid>
	</source>
	<owner>
		<flickrid>rtz</flickrid>
		<name>?</name>
	</owner>
	<size>
		<width>2048</width>
		<height>1024</height>
		<deep>3</deep>
	</size>
	<segmented>0</segmented>
	<object>
		<name>car</name>
		<pose>Frontal</pose>
		<truncated>0</truncated>
		<difficult>0</difficult>
		<bndbox>
			<xmin>678</xmin>
			<ymin>410</ymin>
			<xmax>790</xmax>
			<ymax>463</ymax>
		</bndbox>
	</object>
	<object>
		<name>car</name>
		<pose>Frontal</pose>
		<truncated>0</truncated>
		<difficult>0</difficult>
		<bndbox>
			<xmin>506</xmin>
			<ymin>442</ymin>
			<xmax>554</xmax>
			<ymax>475</ymax>
		</bndbox>
	</object>
	<object>
		<name>car</name>
		<pose>Frontal</pose>
		<truncated>0</truncated>
		<difficult>0</difficult>
		<bndbox>
			<xmin>1</xmin>
			<ymin>413</ymin>
			<xmax>193</xmax>
			<ymax>679</ymax>
		</bndbox>
	</object>
	<object>
		<name>car</name>
		<pose>Frontal</pose>
		<truncated>0</truncated>
		<difficult>0</difficult>
		<bndbox>
			<xmin>926</xmin>
			<ymin>424</ymin>
			<xmax>967</xmax>
			<ymax>461</ymax>
		</bndbox>
	</object>
	<object>
		<name>car</name>
		<pose>Frontal</pose>
		<truncated>0</truncated>
		<difficult>0</difficult>
		<bndbox>
			<xmin>983</xmin>
			<ymin>432</ymin>
			<xmax>1021</xmax>
			<ymax>457</ymax>
		</bndbox>
	</object>
	<object>
		<name>car</name>
		<pose>Frontal</pose>
		<truncated>0</truncated>
		<difficult>0</difficult>
		<bndbox>
			<xmin>1022</xmin>
			<ymin>429</ymin>
			<xmax>1052</xmax>
			<ymax>453</ymax>
		</bndbox>
	</object>
	<object>
		<name>car</name>
		<pose>Frontal</pose>
		<truncated>0</truncated>
		<difficult>0</difficult>
		<bndbox>
			<xmin>1048</xmin>
			<ymin>428</ymin>
			<xmax>1079</xmax>
			<ymax>455</ymax>
		</bndbox>
	</object>
	<object>
		<name>rider</name>
		<pose>Frontal</pose>
		<truncated>0</truncated>
		<difficult>0</difficult>
		<bndbox>
			<xmin>840</xmin>
			<ymin>425</ymin>
			<xmax>856</xmax>
			<ymax>474</ymax>
		</bndbox>
	</object>
	<object>
		<name>bicycle</name>
		<pose>Frontal</pose>
		<truncated>0</truncated>
		<difficult>0</difficult>
		<bndbox>
			<xmin>840</xmin>
			<ymin>452</ymin>
			<xmax>854</xmax>
			<ymax>479</ymax>
		</bndbox>
	</object>
</annotation>