<annotation>
	<folder>VOC2007</folder>
	<filename>target_erfurt_000001_000019_leftImg8bit_foggy_beta_0.02.jpg</filename>
	<source>
		<database>The VOC2007 Database</database>
		<annotation>PASCAL VOC2007</annotation>
		<image>flickr</image>
		<flickrid>0</flickrid>
	</source>
	<owner>
		<flickrid>rtz</flickrid>
		<name>?</name>
	</owner>
	<size>
		<width>2048</width>
		<height>1024</height>
		<deep>3</deep>
	</size>
	<segmented>0</segmented>
	<object>
		<name>car</name>
		<pose>Frontal</pose>
		<truncated>0</truncated>
		<difficult>0</difficult>
		<bndbox>
			<xmin>755</xmin>
			<ymin>429</ymin>
			<xmax>783</xmax>
			<ymax>449</ymax>
		</bndbox>
	</object>
	<object>
		<name>car</name>
		<pose>Frontal</pose>
		<truncated>0</truncated>
		<difficult>0</difficult>
		<bndbox>
			<xmin>777</xmin>
			<ymin>422</ymin>
			<xmax>811</xmax>
			<ymax>451</ymax>
		</bndbox>
	</object>
	<object>
		<name>car</name>
		<pose>Frontal</pose>
		<truncated>0</truncated>
		<difficult>0</difficult>
		<bndbox>
			<xmin>817</xmin>
			<ymin>414</ymin>
			<xmax>856</xmax>
			<ymax>450</ymax>
		</bndbox>
	</object>
	<object>
		<name>car</name>
		<pose>Frontal</pose>
		<truncated>0</truncated>
		<difficult>0</difficult>
		<bndbox>
			<xmin>893</xmin>
			<ymin>415</ymin>
			<xmax>932</xmax>
			<ymax>453</ymax>
		</bndbox>
	</object>
	<object>
		<name>car</name>
		<pose>Frontal</pose>
		<truncated>0</truncated>
		<difficult>0</difficult>
		<bndbox>
			<xmin>911</xmin>
			<ymin>418</ymin>
			<xmax>954</xmax>
			<ymax>451</ymax>
		</bndbox>
	</object>
	<object>
		<name>car</name>
		<pose>Frontal</pose>
		<truncated>0</truncated>
		<difficult>0</difficult>
		<bndbox>
			<xmin>989</xmin>
			<ymin>409</ymin>
			<xmax>1044</xmax>
			<ymax>465</ymax>
		</bndbox>
	</object>
	<object>
		<name>car</name>
		<pose>Frontal</pose>
		<truncated>0</truncated>
		<difficult>0</difficult>
		<bndbox>
			<xmin>1033</xmin>
			<ymin>383</ymin>
			<xmax>1127</xmax>
			<ymax>476</ymax>
		</bndbox>
	</object>
	<object>
		<name>car</name>
		<pose>Frontal</pose>
		<truncated>0</truncated>
		<difficult>0</difficult>
		<bndbox>
			<xmin>1152</xmin>
			<ymin>388</ymin>
			<xmax>1239</xmax>
			<ymax>519</ymax>
		</bndbox>
	</object>
	<object>
		<name>car</name>
		<pose>Frontal</pose>
		<truncated>0</truncated>
		<difficult>0</difficult>
		<bndbox>
			<xmin>1205</xmin>
			<ymin>349</ymin>
			<xmax>1410</xmax>
			<ymax>538</ymax>
		</bndbox>
	</object>
	<object>
		<name>car</name>
		<pose>Frontal</pose>
		<truncated>0</truncated>
		<difficult>0</difficult>
		<bndbox>
			<xmin>1314</xmin>
			<ymin>362</ymin>
			<xmax>1582</xmax>
			<ymax>581</ymax>
		</bndbox>
	</object>
	<object>
		<name>person</name>
		<pose>Frontal</pose>
		<truncated>0</truncated>
		<difficult>0</difficult>
		<bndbox>
			<xmin>1713</xmin>
			<ymin>335</ymin>
			<xmax>1780</xmax>
			<ymax>515</ymax>
		</bndbox>
	</object>
	<object>
		<name>person</name>
		<pose>Frontal</pose>
		<truncated>0</truncated>
		<difficult>0</difficult>
		<bndbox>
			<xmin>1658</xmin>
			<ymin>316</ymin>
			<xmax>1753</xmax>
			<ymax>525</ymax>
		</bndbox>
	</object>
	<object>
		<name>person</name>
		<pose>Frontal</pose>
		<truncated>0</truncated>
		<difficult>0</difficult>
		<bndbox>
			<xmin>1789</xmin>
			<ymin>328</ymin>
			<xmax>1855</xmax>
			<ymax>520</ymax>
		</bndbox>
	</object>
</annotation>