<annotation>
	<folder>VOC2007</folder>
	<filename>source_strasbourg_000001_009246_leftImg8bit.jpg</filename>
	<source>
		<database>The VOC2007 Database</database>
		<annotation>PASCAL VOC2007</annotation>
		<image>flickr</image>
		<flickrid>0</flickrid>
	</source>
	<owner>
		<flickrid>rtz</flickrid>
		<name>?</name>
	</owner>
	<size>
		<width>2048</width>
		<height>1024</height>
		<deep>3</deep>
	</size>
	<segmented>0</segmented>
	<object>
		<name>car</name>
		<pose>Frontal</pose>
		<truncated>0</truncated>
		<difficult>0</difficult>
		<bndbox>
			<xmin>888</xmin>
			<ymin>375</ymin>
			<xmax>957</xmax>
			<ymax>423</ymax>
		</bndbox>
	</object>
	<object>
		<name>person</name>
		<pose>Frontal</pose>
		<truncated>0</truncated>
		<difficult>0</difficult>
		<bndbox>
			<xmin>960</xmin>
			<ymin>374</ymin>
			<xmax>978</xmax>
			<ymax>425</ymax>
		</bndbox>
	</object>
	<object>
		<name>person</name>
		<pose>Frontal</pose>
		<truncated>0</truncated>
		<difficult>0</difficult>
		<bndbox>
			<xmin>1110</xmin>
			<ymin>380</ymin>
			<xmax>1131</xmax>
			<ymax>407</ymax>
		</bndbox>
	</object>
	<object>
		<name>car</name>
		<pose>Frontal</pose>
		<truncated>0</truncated>
		<difficult>0</difficult>
		<bndbox>
			<xmin>1076</xmin>
			<ymin>394</ymin>
			<xmax>1113</xmax>
			<ymax>412</ymax>
		</bndbox>
	</object>
	<object>
		<name>car</name>
		<pose>Frontal</pose>
		<truncated>0</truncated>
		<difficult>0</difficult>
		<bndbox>
			<xmin>1107</xmin>
			<ymin>391</ymin>
			<xmax>1186</xmax>
			<ymax>428</ymax>
		</bndbox>
	</object>
	<object>
		<name>car</name>
		<pose>Frontal</pose>
		<truncated>0</truncated>
		<difficult>0</difficult>
		<bndbox>
			<xmin>1091</xmin>
			<ymin>391</ymin>
			<xmax>1147</xmax>
			<ymax>434</ymax>
		</bndbox>
	</object>
	<object>
		<name>person</name>
		<pose>Frontal</pose>
		<truncated>0</truncated>
		<difficult>0</difficult>
		<bndbox>
			<xmin>1109</xmin>
			<ymin>393</ymin>
			<xmax>1126</xmax>
			<ymax>447</ymax>
		</bndbox>
	</object>
	<object>
		<name>person</name>
		<pose>Frontal</pose>
		<truncated>0</truncated>
		<difficult>0</difficult>
		<bndbox>
			<xmin>1039</xmin>
			<ymin>380</ymin>
			<xmax>1060</xmax>
			<ymax>440</ymax>
		</bndbox>
	</object>
	<object>
		<name>person</name>
		<pose>Frontal</pose>
		<truncated>0</truncated>
		<difficult>0</difficult>
		<bndbox>
			<xmin>1042</xmin>
			<ymin>387</ymin>
			<xmax>1065</xmax>
			<ymax>442</ymax>
		</bndbox>
	</object>
	<object>
		<name>person</name>
		<pose>Frontal</pose>
		<truncated>0</truncated>
		<difficult>0</difficult>
		<bndbox>
			<xmin>1245</xmin>
			<ymin>383</ymin>
			<xmax>1264</xmax>
			<ymax>420</ymax>
		</bndbox>
	</object>
	<object>
		<name>person</name>
		<pose>Frontal</pose>
		<truncated>0</truncated>
		<difficult>0</difficult>
		<bndbox>
			<xmin>1204</xmin>
			<ymin>385</ymin>
			<xmax>1216</xmax>
			<ymax>417</ymax>
		</bndbox>
	</object>
	<object>
		<name>bicycle</name>
		<pose>Frontal</pose>
		<truncated>0</truncated>
		<difficult>0</difficult>
		<bndbox>
			<xmin>1211</xmin>
			<ymin>412</ymin>
			<xmax>1234</xmax>
			<ymax>467</ymax>
		</bndbox>
	</object>
	<object>
		<name>person</name>
		<pose>Frontal</pose>
		<truncated>0</truncated>
		<difficult>0</difficult>
		<bndbox>
			<xmin>1390</xmin>
			<ymin>345</ymin>
			<xmax>1464</xmax>
			<ymax>502</ymax>
		</bndbox>
	</object>
	<object>
		<name>bicycle</name>
		<pose>Frontal</pose>
		<truncated>0</truncated>
		<difficult>0</difficult>
		<bndbox>
			<xmin>1335</xmin>
			<ymin>407</ymin>
			<xmax>1415</xmax>
			<ymax>545</ymax>
		</bndbox>
	</object>
</annotation>