<annotation>
	<folder>VOC2007</folder>
	<filename>source_stuttgart_000178_000019_leftImg8bit.jpg</filename>
	<source>
		<database>The VOC2007 Database</database>
		<annotation>PASCAL VOC2007</annotation>
		<image>flickr</image>
		<flickrid>0</flickrid>
	</source>
	<owner>
		<flickrid>rtz</flickrid>
		<name>?</name>
	</owner>
	<size>
		<width>2048</width>
		<height>1024</height>
		<deep>3</deep>
	</size>
	<segmented>0</segmented>
	<object>
		<name>rider</name>
		<pose>Frontal</pose>
		<truncated>0</truncated>
		<difficult>0</difficult>
		<bndbox>
			<xmin>1482</xmin>
			<ymin>409</ymin>
			<xmax>1501</xmax>
			<ymax>454</ymax>
		</bndbox>
	</object>
	<object>
		<name>bicycle</name>
		<pose>Frontal</pose>
		<truncated>0</truncated>
		<difficult>0</difficult>
		<bndbox>
			<xmin>1485</xmin>
			<ymin>433</ymin>
			<xmax>1498</xmax>
			<ymax>460</ymax>
		</bndbox>
	</object>
	<object>
		<name>truck</name>
		<pose>Frontal</pose>
		<truncated>0</truncated>
		<difficult>0</difficult>
		<bndbox>
			<xmin>1036</xmin>
			<ymin>369</ymin>
			<xmax>1067</xmax>
			<ymax>409</ymax>
		</bndbox>
	</object>
	<object>
		<name>car</name>
		<pose>Frontal</pose>
		<truncated>0</truncated>
		<difficult>0</difficult>
		<bndbox>
			<xmin>1052</xmin>
			<ymin>353</ymin>
			<xmax>1176</xmax>
			<ymax>492</ymax>
		</bndbox>
	</object>
	<object>
		<name>car</name>
		<pose>Frontal</pose>
		<truncated>0</truncated>
		<difficult>0</difficult>
		<bndbox>
			<xmin>1147</xmin>
			<ymin>407</ymin>
			<xmax>1321</xmax>
			<ymax>524</ymax>
		</bndbox>
	</object>
	<object>
		<name>car</name>
		<pose>Frontal</pose>
		<truncated>0</truncated>
		<difficult>0</difficult>
		<bndbox>
			<xmin>846</xmin>
			<ymin>421</ymin>
			<xmax>879</xmax>
			<ymax>450</ymax>
		</bndbox>
	</object>
	<object>
		<name>car</name>
		<pose>Frontal</pose>
		<truncated>0</truncated>
		<difficult>0</difficult>
		<bndbox>
			<xmin>783</xmin>
			<ymin>422</ymin>
			<xmax>820</xmax>
			<ymax>451</ymax>
		</bndbox>
	</object>
	<object>
		<name>car</name>
		<pose>Frontal</pose>
		<truncated>0</truncated>
		<difficult>0</difficult>
		<bndbox>
			<xmin>622</xmin>
			<ymin>427</ymin>
			<xmax>641</xmax>
			<ymax>460</ymax>
		</bndbox>
	</object>
	<object>
		<name>truck</name>
		<pose>Frontal</pose>
		<truncated>0</truncated>
		<difficult>0</difficult>
		<bndbox>
			<xmin>1759</xmin>
			<ymin>163</ymin>
			<xmax>2047</xmax>
			<ymax>569</ymax>
		</bndbox>
	</object>
	<object>
		<name>car</name>
		<pose>Frontal</pose>
		<truncated>0</truncated>
		<difficult>0</difficult>
		<bndbox>
			<xmin>762</xmin>
			<ymin>421</ymin>
			<xmax>781</xmax>
			<ymax>448</ymax>
		</bndbox>
	</object>
	<object>
		<name>car</name>
		<pose>Frontal</pose>
		<truncated>0</truncated>
		<difficult>0</difficult>
		<bndbox>
			<xmin>297</xmin>
			<ymin>389</ymin>
			<xmax>399</xmax>
			<ymax>450</ymax>
		</bndbox>
	</object>
	<object>
		<name>person</name>
		<pose>Frontal</pose>
		<truncated>0</truncated>
		<difficult>0</difficult>
		<bndbox>
			<xmin>334</xmin>
			<ymin>409</ymin>
			<xmax>348</xmax>
			<ymax>452</ymax>
		</bndbox>
	</object>
	<object>
		<name>person</name>
		<pose>Frontal</pose>
		<truncated>0</truncated>
		<difficult>0</difficult>
		<bndbox>
			<xmin>352</xmin>
			<ymin>416</ymin>
			<xmax>374</xmax>
			<ymax>470</ymax>
		</bndbox>
	</object>
	<object>
		<name>person</name>
		<pose>Frontal</pose>
		<truncated>0</truncated>
		<difficult>0</difficult>
		<bndbox>
			<xmin>474</xmin>
			<ymin>409</ymin>
			<xmax>494</xmax>
			<ymax>469</ymax>
		</bndbox>
	</object>
	<object>
		<name>car</name>
		<pose>Frontal</pose>
		<truncated>0</truncated>
		<difficult>0</difficult>
		<bndbox>
			<xmin>550</xmin>
			<ymin>417</ymin>
			<xmax>609</xmax>
			<ymax>463</ymax>
		</bndbox>
	</object>
	<object>
		<name>car</name>
		<pose>Frontal</pose>
		<truncated>0</truncated>
		<difficult>0</difficult>
		<bndbox>
			<xmin>821</xmin>
			<ymin>397</ymin>
			<xmax>1143</xmax>
			<ymax>636</ymax>
		</bndbox>
	</object>
</annotation>