<annotation>
	<folder>VOC2007</folder>
	<filename>target_dusseldorf_000028_000019_leftImg8bit_foggy_beta_0.02.jpg</filename>
	<source>
		<database>The VOC2007 Database</database>
		<annotation>PASCAL VOC2007</annotation>
		<image>flickr</image>
		<flickrid>0</flickrid>
	</source>
	<owner>
		<flickrid>rtz</flickrid>
		<name>?</name>
	</owner>
	<size>
		<width>2048</width>
		<height>1024</height>
		<deep>3</deep>
	</size>
	<segmented>0</segmented>
	<object>
		<name>car</name>
		<pose>Frontal</pose>
		<truncated>0</truncated>
		<difficult>0</difficult>
		<bndbox>
			<xmin>529</xmin>
			<ymin>425</ymin>
			<xmax>606</xmax>
			<ymax>503</ymax>
		</bndbox>
	</object>
	<object>
		<name>car</name>
		<pose>Frontal</pose>
		<truncated>0</truncated>
		<difficult>0</difficult>
		<bndbox>
			<xmin>405</xmin>
			<ymin>409</ymin>
			<xmax>545</xmax>
			<ymax>512</ymax>
		</bndbox>
	</object>
	<object>
		<name>car</name>
		<pose>Frontal</pose>
		<truncated>0</truncated>
		<difficult>0</difficult>
		<bndbox>
			<xmin>212</xmin>
			<ymin>404</ymin>
			<xmax>428</xmax>
			<ymax>529</ymax>
		</bndbox>
	</object>
	<object>
		<name>bicycle</name>
		<pose>Frontal</pose>
		<truncated>0</truncated>
		<difficult>0</difficult>
		<bndbox>
			<xmin>24</xmin>
			<ymin>444</ymin>
			<xmax>157</xmax>
			<ymax>556</ymax>
		</bndbox>
	</object>
	<object>
		<name>car</name>
		<pose>Frontal</pose>
		<truncated>0</truncated>
		<difficult>0</difficult>
		<bndbox>
			<xmin>866</xmin>
			<ymin>413</ymin>
			<xmax>922</xmax>
			<ymax>451</ymax>
		</bndbox>
	</object>
	<object>
		<name>car</name>
		<pose>Frontal</pose>
		<truncated>0</truncated>
		<difficult>0</difficult>
		<bndbox>
			<xmin>1139</xmin>
			<ymin>412</ymin>
			<xmax>1164</xmax>
			<ymax>427</ymax>
		</bndbox>
	</object>
	<object>
		<name>car</name>
		<pose>Frontal</pose>
		<truncated>0</truncated>
		<difficult>0</difficult>
		<bndbox>
			<xmin>986</xmin>
			<ymin>413</ymin>
			<xmax>1154</xmax>
			<ymax>468</ymax>
		</bndbox>
	</object>
	<object>
		<name>car</name>
		<pose>Frontal</pose>
		<truncated>0</truncated>
		<difficult>0</difficult>
		<bndbox>
			<xmin>888</xmin>
			<ymin>406</ymin>
			<xmax>994</xmax>
			<ymax>481</ymax>
		</bndbox>
	</object>
	<object>
		<name>car</name>
		<pose>Frontal</pose>
		<truncated>0</truncated>
		<difficult>0</difficult>
		<bndbox>
			<xmin>667</xmin>
			<ymin>368</ymin>
			<xmax>813</xmax>
			<ymax>496</ymax>
		</bndbox>
	</object>
	<object>
		<name>car</name>
		<pose>Frontal</pose>
		<truncated>0</truncated>
		<difficult>0</difficult>
		<bndbox>
			<xmin>1244</xmin>
			<ymin>419</ymin>
			<xmax>1277</xmax>
			<ymax>456</ymax>
		</bndbox>
	</object>
	<object>
		<name>car</name>
		<pose>Frontal</pose>
		<truncated>0</truncated>
		<difficult>0</difficult>
		<bndbox>
			<xmin>1200</xmin>
			<ymin>416</ymin>
			<xmax>1255</xmax>
			<ymax>453</ymax>
		</bndbox>
	</object>
	<object>
		<name>car</name>
		<pose>Frontal</pose>
		<truncated>0</truncated>
		<difficult>0</difficult>
		<bndbox>
			<xmin>1160</xmin>
			<ymin>414</ymin>
			<xmax>1256</xmax>
			<ymax>490</ymax>
		</bndbox>
	</object>
	<object>
		<name>car</name>
		<pose>Frontal</pose>
		<truncated>0</truncated>
		<difficult>0</difficult>
		<bndbox>
			<xmin>1313</xmin>
			<ymin>415</ymin>
			<xmax>1378</xmax>
			<ymax>489</ymax>
		</bndbox>
	</object>
	<object>
		<name>car</name>
		<pose>Frontal</pose>
		<truncated>0</truncated>
		<difficult>0</difficult>
		<bndbox>
			<xmin>1447</xmin>
			<ymin>413</ymin>
			<xmax>1491</xmax>
			<ymax>485</ymax>
		</bndbox>
	</object>
	<object>
		<name>car</name>
		<pose>Frontal</pose>
		<truncated>0</truncated>
		<difficult>0</difficult>
		<bndbox>
			<xmin>1604</xmin>
			<ymin>410</ymin>
			<xmax>1690</xmax>
			<ymax>478</ymax>
		</bndbox>
	</object>
	<object>
		<name>car</name>
		<pose>Frontal</pose>
		<truncated>0</truncated>
		<difficult>0</difficult>
		<bndbox>
			<xmin>1465</xmin>
			<ymin>389</ymin>
			<xmax>1604</xmax>
			<ymax>493</ymax>
		</bndbox>
	</object>
	<object>
		<name>car</name>
		<pose>Frontal</pose>
		<truncated>0</truncated>
		<difficult>0</difficult>
		<bndbox>
			<xmin>1331</xmin>
			<ymin>400</ymin>
			<xmax>1456</xmax>
			<ymax>499</ymax>
		</bndbox>
	</object>
	<object>
		<name>car</name>
		<pose>Frontal</pose>
		<truncated>0</truncated>
		<difficult>0</difficult>
		<bndbox>
			<xmin>1674</xmin>
			<ymin>412</ymin>
			<xmax>1837</xmax>
			<ymax>505</ymax>
		</bndbox>
	</object>
	<object>
		<name>car</name>
		<pose>Frontal</pose>
		<truncated>0</truncated>
		<difficult>0</difficult>
		<bndbox>
			<xmin>1517</xmin>
			<ymin>411</ymin>
			<xmax>1669</xmax>
			<ymax>507</ymax>
		</bndbox>
	</object>
	<object>
		<name>car</name>
		<pose>Frontal</pose>
		<truncated>0</truncated>
		<difficult>0</difficult>
		<bndbox>
			<xmin>1784</xmin>
			<ymin>418</ymin>
			<xmax>1974</xmax>
			<ymax>520</ymax>
		</bndbox>
	</object>
	<object>
		<name>car</name>
		<pose>Frontal</pose>
		<truncated>0</truncated>
		<difficult>0</difficult>
		<bndbox>
			<xmin>1919</xmin>
			<ymin>404</ymin>
			<xmax>2049</xmax>
			<ymax>545</ymax>
		</bndbox>
	</object>
</annotation>