<annotation>
	<folder>VOC2007</folder>
	<filename>target_strasbourg_000000_031223_leftImg8bit_foggy_beta_0.02.jpg</filename>
	<source>
		<database>The VOC2007 Database</database>
		<annotation>PASCAL VOC2007</annotation>
		<image>flickr</image>
		<flickrid>0</flickrid>
	</source>
	<owner>
		<flickrid>rtz</flickrid>
		<name>?</name>
	</owner>
	<size>
		<width>2048</width>
		<height>1024</height>
		<deep>3</deep>
	</size>
	<segmented>0</segmented>
	<object>
		<name>car</name>
		<pose>Frontal</pose>
		<truncated>0</truncated>
		<difficult>0</difficult>
		<bndbox>
			<xmin>1181</xmin>
			<ymin>378</ymin>
			<xmax>1212</xmax>
			<ymax>403</ymax>
		</bndbox>
	</object>
	<object>
		<name>train</name>
		<pose>Frontal</pose>
		<truncated>0</truncated>
		<difficult>0</difficult>
		<bndbox>
			<xmin>1191</xmin>
			<ymin>338</ymin>
			<xmax>1306</xmax>
			<ymax>427</ymax>
		</bndbox>
	</object>
	<object>
		<name>person</name>
		<pose>Frontal</pose>
		<truncated>0</truncated>
		<difficult>0</difficult>
		<bndbox>
			<xmin>1416</xmin>
			<ymin>379</ymin>
			<xmax>1434</xmax>
			<ymax>411</ymax>
		</bndbox>
	</object>
	<object>
		<name>person</name>
		<pose>Frontal</pose>
		<truncated>0</truncated>
		<difficult>0</difficult>
		<bndbox>
			<xmin>1435</xmin>
			<ymin>372</ymin>
			<xmax>1449</xmax>
			<ymax>411</ymax>
		</bndbox>
	</object>
	<object>
		<name>rider</name>
		<pose>Frontal</pose>
		<truncated>0</truncated>
		<difficult>0</difficult>
		<bndbox>
			<xmin>1414</xmin>
			<ymin>383</ymin>
			<xmax>1434</xmax>
			<ymax>442</ymax>
		</bndbox>
	</object>
	<object>
		<name>bicycle</name>
		<pose>Frontal</pose>
		<truncated>0</truncated>
		<difficult>0</difficult>
		<bndbox>
			<xmin>1418</xmin>
			<ymin>412</ymin>
			<xmax>1427</xmax>
			<ymax>441</ymax>
		</bndbox>
	</object>
	<object>
		<name>car</name>
		<pose>Frontal</pose>
		<truncated>0</truncated>
		<difficult>0</difficult>
		<bndbox>
			<xmin>863</xmin>
			<ymin>357</ymin>
			<xmax>936</xmax>
			<ymax>459</ymax>
		</bndbox>
	</object>
	<object>
		<name>car</name>
		<pose>Frontal</pose>
		<truncated>0</truncated>
		<difficult>0</difficult>
		<bndbox>
			<xmin>753</xmin>
			<ymin>323</ymin>
			<xmax>922</xmax>
			<ymax>479</ymax>
		</bndbox>
	</object>
	<object>
		<name>car</name>
		<pose>Frontal</pose>
		<truncated>0</truncated>
		<difficult>0</difficult>
		<bndbox>
			<xmin>761</xmin>
			<ymin>346</ymin>
			<xmax>890</xmax>
			<ymax>504</ymax>
		</bndbox>
	</object>
	<object>
		<name>car</name>
		<pose>Frontal</pose>
		<truncated>0</truncated>
		<difficult>0</difficult>
		<bndbox>
			<xmin>553</xmin>
			<ymin>298</ymin>
			<xmax>833</xmax>
			<ymax>550</ymax>
		</bndbox>
	</object>
	<object>
		<name>car</name>
		<pose>Frontal</pose>
		<truncated>0</truncated>
		<difficult>0</difficult>
		<bndbox>
			<xmin>78</xmin>
			<ymin>280</ymin>
			<xmax>684</xmax>
			<ymax>706</ymax>
		</bndbox>
	</object>
	<object>
		<name>car</name>
		<pose>Frontal</pose>
		<truncated>0</truncated>
		<difficult>0</difficult>
		<bndbox>
			<xmin>1</xmin>
			<ymin>291</ymin>
			<xmax>228</xmax>
			<ymax>878</ymax>
		</bndbox>
	</object>
	<object>
		<name>car</name>
		<pose>Frontal</pose>
		<truncated>0</truncated>
		<difficult>0</difficult>
		<bndbox>
			<xmin>927</xmin>
			<ymin>257</ymin>
			<xmax>1151</xmax>
			<ymax>511</ymax>
		</bndbox>
	</object>
</annotation>